pulserver/__init__.py
pulserver/_cli.py
pulserver/_opts.py
pulserver/_version.py
pulserver/_apps/SPGR2D.py
pulserver/_core/__init__.py
pulserver/_core/_autoseg.py
pulserver/_core/_ceq.py
pulserver/_core/_header.py
pulserver/_core/_sequence.py
pulserver/_safety/__init__.py
pulserver/_safety/_gehc.py
pulserver/_server/__init__.py
pulserver/_server/_server.py
pulserver/blocks/__init__.py
pulserver/blocks/_grad/_make_spiral.py
pulserver/blocks/_misc/__init__.py
pulserver/blocks/_misc/_calc_delay.py
pulserver/blocks/_misc/_make_spoiler_gradient.py
pulserver/blocks/_phaseenc/__init__.py
pulserver/blocks/_phaseenc/_make_phase_blip.py
pulserver/blocks/_phaseenc/_make_phase_encoding.py
pulserver/blocks/_readout/__init__.py
pulserver/blocks/_readout/_make_line_readout.py
pulserver/blocks/_readout/_make_spiral_readout.py
pulserver/blocks/_readout/rosette_readout.py
pulserver/blocks/_rfpulse/__init__.py
pulserver/blocks/_rfpulse/_make_slr_pulse.py
pulserver/blocks/_rfpulse/_make_spsp_pulse.py
pulserver/blocks/_rfpulse/_plot.py
pulserver/blocks/_rfpulse/_spsp/__init__.py
pulserver/blocks/_rfpulse/_spsp/_slr.py
pulserver/blocks/_rfpulse/_spsp/_utils.py
pulserver/blocks/_rfpulse/_spsp/rf_ripple.py
pulserver/blocks/_rfpulse/_spsp/spec_interp.py
pulserver/blocks/_rfpulse/_spsp/ss_alias.py
pulserver/blocks/_rfpulse/_spsp/ss_design.py
pulserver/blocks/_rfpulse/_spsp/ss_ep.py
pulserver/blocks/_rfpulse/_spsp/ss_filters.py
pulserver/blocks/_rfpulse/_spsp/ss_flyback.py
pulserver/blocks/_rfpulse/_spsp/ss_fourier.py
pulserver/blocks/_rfpulse/_spsp/ss_globals.py
pulserver/blocks/_rfpulse/_spsp/ss_grad.py
pulserver/blocks/_rfpulse/_spsp/ss_spect_correct.py
pulserver/blocks/_rfpulse/_spsp/ss_verse.py
pulserver/parsing/__init__.py
pulserver/parsing/_base.py
pulserver/parsing/_cartesian_params.py
pulserver/plan/__init__.py
pulserver/plan/_cartesian2D.py
pulserver/plan/_cartesian3D.py
pulserver/plan/_noncartesian2D.py
pulserver/plan/_noncartesian3D.py
pulserver/plan/_ordering.py
pulserver-0.1.12.dist-info/LICENSE.txt
pulserver-0.1.12.dist-info/METADATA
pulserver-0.1.12.dist-info/WHEEL
pulserver-0.1.12.dist-info/entry_points.txt
pulserver-0.1.12.dist-info/top_level.txt
pulserver-0.1.12.dist-info/RECORD
