Metadata-Version: 2.1
Name: pulserver
Version: 0.1.12
Summary: A PyPulseq-based client/server MR sequence design toolbox.
Author-email: Matteo Cencini <matteo.cencini@gmail.com>
Project-URL: Homepage, https://github.com/INFN-MRI/pulserver
Project-URL: Bug Reports, https://github.com/INFN-MRI/pulserver/issues
Project-URL: Source, https://github.com/INFN-MRI/pulserver
Keywords: pulseq,mri,sequence-design,pulse-sequences,mri-sequences
Classifier: Development Status :: 3 - Alpha
Classifier: Intended Audience :: Developers
Classifier: License :: OSI Approved :: MIT License
Classifier: Programming Language :: Python :: 3.10
Classifier: Programming Language :: Python :: 3.11
Classifier: Programming Language :: Python :: 3.12
Requires-Python: >=3.10
License-File: LICENSE.txt
Requires-Dist: click
Requires-Dist: numpy<2.0
Requires-Dist: scipy<1.14
Requires-Dist: numba
Requires-Dist: pypulseq
Requires-Dist: pulpy
Requires-Dist: mri-nufft
Requires-Dist: mrd-python
Requires-Dist: ipywidgets
Provides-Extra: dev
Requires-Dist: black; extra == "dev"
Requires-Dist: isort; extra == "dev"
Provides-Extra: doc
Requires-Dist: sphinx; extra == "doc"
Requires-Dist: pydata-sphinx-theme; extra == "doc"
Requires-Dist: myst-nb; extra == "doc"
Requires-Dist: matplotlib; extra == "doc"
Requires-Dist: mrtwin; extra == "doc"
Requires-Dist: sphinx-copybutton; extra == "doc"
Provides-Extra: test
Requires-Dist: pytest; extra == "test"
Requires-Dist: pytest-black; extra == "test"
Requires-Dist: pytest-cov; extra == "test"
Requires-Dist: pytest-sugar; extra == "test"
Requires-Dist: pytest-xdist; extra == "test"
